codemagic/__init__.py
codemagic/__version__.py
codemagic/__version__.py-e
codemagic/apple/__init__.py
codemagic/apple/app_store_connect/__init__.py
codemagic/apple/app_store_connect/api_client.py
codemagic/apple/app_store_connect/api_error.py
codemagic/apple/app_store_connect/api_session.py
codemagic/apple/app_store_connect/app_store_publishing/__init__.py
codemagic/apple/app_store_connect/app_store_publishing/app_store_version_phased_releases.py
codemagic/apple/app_store_connect/apps/__init__.py
codemagic/apple/app_store_connect/apps/apps.py
codemagic/apple/app_store_connect/builds/__init__.py
codemagic/apple/app_store_connect/builds/builds.py
codemagic/apple/app_store_connect/json_web_token_manager.py
codemagic/apple/app_store_connect/provisioning/__init__.py
codemagic/apple/app_store_connect/provisioning/bundle_id_capabilities.py
codemagic/apple/app_store_connect/provisioning/bundle_ids.py
codemagic/apple/app_store_connect/provisioning/devices.py
codemagic/apple/app_store_connect/provisioning/profiles.py
codemagic/apple/app_store_connect/provisioning/signing_certificates.py
codemagic/apple/app_store_connect/resource_manager.py
codemagic/apple/app_store_connect/testflight/__init__.py
codemagic/apple/app_store_connect/testflight/beta_groups.py
codemagic/apple/app_store_connect/type_declarations.py
codemagic/apple/app_store_connect/versioning/__init__.py
codemagic/apple/app_store_connect/versioning/app_store_version_localizations.py
codemagic/apple/app_store_connect/versioning/app_store_version_submissions.py
codemagic/apple/app_store_connect/versioning/app_store_versions.py
codemagic/apple/app_store_connect/versioning/beta_app_review_submissions.py
codemagic/apple/app_store_connect/versioning/beta_build_localizations.py
codemagic/apple/app_store_connect/versioning/pre_release_versions.py
codemagic/apple/app_store_connect/versioning/review_submission_items.py
codemagic/apple/app_store_connect/versioning/review_submissions.py
codemagic/apple/resources/__init__.py
codemagic_cli_tools-0.62.1.dist-info/METADATA
codemagic_cli_tools-0.62.1.dist-info/WHEEL
codemagic_cli_tools-0.62.1.dist-info/entry_points.txt
codemagic_cli_tools-0.62.1.dist-info/licenses/LICENSE
codemagic_cli_tools-0.62.1.dist-info/RECORD
