Metadata-Version: 2.4
Name: codemagic-cli-tools
Version: 0.62.1
Summary: CLI tools used in Codemagic builds
License: GPL-3.0-or-later
License-File: LICENSE
Author: Priit Lätt
Author-email: priit@nevercode.io
Requires-Python: >=3.8,<4.0
Classifier: License :: OSI Approved :: GNU General Public License v3 or later (GPLv3+)
Classifier: Programming Language :: Python :: 3
Classifier: Programming Language :: Python :: 3.8
Classifier: Programming Language :: Python :: 3.9
Classifier: Programming Language :: Python :: 3.10
Classifier: Programming Language :: Python :: 3.11
Classifier: Programming Language :: Python :: 3.12
Classifier: Programming Language :: Python :: 3.13
Classifier: Programming Language :: Python :: 3.14
Requires-Dist: cryptography (>=38.0.0)
Requires-Dist: google-api-python-client (>=2.84.0)
Requires-Dist: httplib2 (>=0.19.0)
Requires-Dist: oauth2client (>=4.1.3)
Requires-Dist: packaging (>=22.0)
Requires-Dist: psutil (>=5.8.0)
Requires-Dist: pyjwt (>=2.4.0,<3.0.0)
Requires-Dist: python-dateutil (>=2.9.0)
Requires-Dist: requests (>=2.25)
Project-URL: Changelog, https://github.com/codemagic-ci-cd/cli-tools/blob/master/CHANGELOG.md
Project-URL: Documentation, https://github.com/codemagic-ci-cd/cli-tools/tree/master/docs#cli-tools
Project-URL: Homepage, https://github.com/codemagic-ci-cd/cli-tools
Project-URL: Issue Tracker, https://github.com/codemagic-ci-cd/cli-tools/issues
Project-URL: Repository, https://github.com/codemagic-ci-cd/cli-tools
